ram.py
random_access_machine-1.0.1.dist-info/METADATA
random_access_machine-1.0.1.dist-info/WHEEL
random_access_machine-1.0.1.dist-info/top_level.txt
random_access_machine-1.0.1.dist-info/RECORD
